setup.py
discogs_client/__init__.py
discogs_client/client.py
discogs_client/exceptions.py
discogs_client/fetchers.py
discogs_client/models.py
discogs_client/utils.py
discogs_client.egg-info/PKG-INFO
discogs_client.egg-info/SOURCES.txt
discogs_client.egg-info/dependency_links.txt
discogs_client.egg-info/requires.txt
discogs_client.egg-info/top_level.txt