Metadata-Version: 1.1
Name: discogs-client
Version: 2.1.0
Summary: Official Python API client for Discogs
Home-page: https://github.com/discogs/discogs_client
Author: Discogs
Author-email: info@discogs.com
License: UNKNOWN
Platform: UNKNOWN
Classifier: Development Status :: 5 - Production/Stable
Classifier: Environment :: Console
Classifier: License :: OSI Approved :: BSD License
Classifier: Natural Language :: English
Classifier: Operating System :: OS Independent
Classifier: Programming Language :: Python
Classifier: Topic :: Communications
Classifier: Topic :: Utilities
